{"totalPosts": 15612, "totalPostsFromIndia": 8752, "totalPostsWithTotalComp": 7173, "lastUpdated": "2024/01/23 00:55:56", "top20Companies": [["Amazon", 662], ["Microsoft", 347], ["Oracle", 209], ["Google", 176], ["Walmart", 169], ["Flipkart", 127], ["Paytm", 122], ["Goldman Sachs", 115], ["Paypal", 102], ["Salesforce", 99], ["Infosys", 97], ["Samsung", 96], ["Adobe", 90], ["Ola", 86], ["Tcs", 79], ["Wipro", 79], ["Oyo", 76], ["Vmware", 72], ["Swiggy", 72], ["Cognizant", 64]], "mostOffersInLastMonth": [["Amazon", 5], ["Infosys", 4], ["Accenture", 4], ["Oracle", 3], ["Google", 3], ["Salesforce", 3], ["Bharatpe", 2], ["Deltax", 2], ["Deutsche Bank", 2], ["Cropin", 2]]}