{"totalPosts": 18435, "totalPostsFromIndia": 9906, "totalPostsWithTotalComp": 8034, "lastUpdated": "2024/12/31 01:07:03", "top20Companies": [["Amazon", 703], ["Microsoft", 459], ["Oracle", 251], ["Google", 247], ["Walmart", 205], ["Flipkart", 143], ["Salesforce", 135], ["Goldman Sachs", 133], ["Paytm", 124], ["Paypal", 115], ["Samsung", 100], ["Infosys", 99], ["Adobe", 98], ["Ola", 87], ["Tcs", 87], ["Wipro", 82], ["Uber", 76], ["Oyo", 76], ["Phonepe", 75], ["Swiggy", 75]], "mostOffersInLastMonth": [["Amazon", 9], ["Microsoft", 6], ["Google", 5], ["Salesforce", 5], ["Paypal", 4], ["Tekion", 3], ["Oracle", 3], ["Flipkart", 3], ["Walmart", 3], ["Expedia", 2]]}