{"totalPosts": 17520, "totalPostsFromIndia": 9516, "totalPostsWithTotalComp": 7747, "lastUpdated": "2024/08/23 01:00:17", "top20Companies": [["Amazon", 677], ["Microsoft", 435], ["Oracle", 237], ["Google", 226], ["Walmart", 194], ["Flipkart", 137], ["Goldman Sachs", 123], ["Paytm", 122], ["Salesforce", 116], ["Paypal", 110], ["Samsung", 99], ["Infosys", 99], ["Adobe", 95], ["Ola", 87], ["Tcs", 87], ["Wipro", 82], ["Oyo", 76], ["Swiggy", 75], ["Vmware", 73], ["Uber", 72]], "mostOffersInLastMonth": [["Microsoft", 15], ["Google", 8], ["Goldman Sachs", 4], ["Epam", 3], ["Salesforce", 2], ["Paypal", 2], ["Servicenow", 2], ["Arista Networks", 2], ["Dunnhumby", 1], ["Razorpay", 1]]}