{"totalPosts": 15582, "totalPostsFromIndia": 8745, "totalPostsWithTotalComp": 7166, "lastUpdated": "2024/01/20 00:53:53", "top20Companies": [["Amazon", 660], ["Microsoft", 347], ["Oracle", 209], ["Google", 176], ["Walmart", 169], ["Flipkart", 127], ["Paytm", 122], ["Goldman Sachs", 115], ["Paypal", 102], ["Salesforce", 99], ["Infosys", 97], ["Samsung", 96], ["Adobe", 90], ["Ola", 86], ["Tcs", 79], ["Wipro", 79], ["Oyo", 76], ["Vmware", 72], ["Swiggy", 72], ["Cognizant", 64]], "mostOffersInLastMonth": [["Infosys", 4], ["Accenture", 4], ["Oracle", 3], ["Google", 3], ["Amazon", 3], ["Salesforce", 3], ["Deltax", 2], ["Deutsche Bank", 2], ["Cropin", 2], ["Tcs", 2]]}