{"totalPosts": 13100, "totalPostsFromIndia": 7650, "totalPostsWithTotalComp": 6318, "lastUpdated": "2023/04/28 12:11:56", "top20Companies": [["Amazon", 609], ["Microsoft", 317], ["Oracle", 192], ["Walmart", 155], ["Google", 145], ["Paytm", 112], ["Goldman Sachs", 108], ["Flipkart", 106], ["Paypal", 92], ["Adobe", 85], ["Samsung", 84], ["Infosys", 79], ["Oyo", 74], ["Wipro", 73], ["Ola", 73], ["Tcs", 71], ["Swiggy", 69], ["Vmware", 68], ["Salesforce", 64], ["Tekion", 57]], "mostOffersInLastMonth": [["Amazon", 5], ["Oracle", 3], ["Startup", 2], ["Microsoft", 2], ["Opentext", 2], ["Samsung", 2], ["Spinny", 2], ["Centre For Development Of Advanced Computing", 1], ["Barclays", 1], ["Zscaler", 1]]}