{"totalPosts": 18268, "totalPostsFromIndia": 9843, "totalPostsWithTotalComp": 7988, "lastUpdated": "2024/12/06 01:12:59", "top20Companies": [["Amazon", 696], ["Microsoft", 454], ["Oracle", 248], ["Google", 242], ["Walmart", 204], ["Flipkart", 142], ["Goldman Sachs", 132], ["Salesforce", 132], ["Paytm", 124], ["Paypal", 112], ["Samsung", 100], ["Infosys", 99], ["Adobe", 96], ["Ola", 87], ["Tcs", 87], ["Wipro", 82], ["Oyo", 76], ["Phonepe", 75], ["Uber", 75], ["Swiggy", 75]], "mostOffersInLastMonth": [["Microsoft", 10], ["Phonepe", 5], ["Goldman Sachs", 4], ["Amazon", 4], ["Walmart", 4], ["Flipkart", 3], ["Salesforce", 3], ["Google", 3], ["Oracle", 3], ["Nielsen", 2]]}